LICENSE
MANIFEST.in
README.md
setup.py
GitToMarkdown/GTM.py
GitToMarkdown/Generator.py
GitToMarkdown/MarkdownUtils.py
GitToMarkdown/Parsers.py
GitToMarkdown/ProgressBar.py
GitToMarkdown/Zipper.py
GitToMarkdown/__init__.py
GitToMarkdown/conf.cfg
GitToMarkdown/errors.py
GitToMarkdown/ext.py
GitToMarkdown/extensions.json
gittomarkdown.egg-info/PKG-INFO
gittomarkdown.egg-info/SOURCES.txt
gittomarkdown.egg-info/dependency_links.txt
gittomarkdown.egg-info/entry_points.txt
gittomarkdown.egg-info/requires.txt
gittomarkdown.egg-info/top_level.txt