Metadata-Version: 2.4
Name: gittomarkdown
Version: 1.0.11
Summary: A tool to generate Markdown documentation from Git repositories
Home-page: https://github.com/the13bit/GitToMarkdown
Author: the13bit
Classifier: Development Status :: 3 - Alpha
Classifier: Intended Audience :: Developers
Classifier: Topic :: Software Development :: Documentation
Classifier: License :: OSI Approved :: MIT License
Classifier: Programming Language :: Python :: 3
Classifier: Programming Language :: Python :: 3.6
Classifier: Programming Language :: Python :: 3.7
Classifier: Programming Language :: Python :: 3.8
Classifier: Programming Language :: Python :: 3.9
Requires-Python: >=3.6
License-File: LICENSE
Requires-Dist: gitpython
Requires-Dist: requests
Requires-Dist: tqdm
Requires-Dist: configparser
Dynamic: author
Dynamic: classifier
Dynamic: description
Dynamic: description-content-type
Dynamic: home-page
Dynamic: license-file
Dynamic: requires-dist
Dynamic: requires-python
Dynamic: summary
